doc/_static/logo.svg
doc/_static/logo_name.svg
doc/_static/README_files/aggline.png
doc/_static/README_files/box.png
doc/_static/README_files/circular_hist.png
doc/_static/README_files/count.png
doc/_static/README_files/default_format.png
doc/_static/README_files/ecdf.png
doc/_static/README_files/fit.png
doc/_static/README_files/formatted_plot.png
doc/_static/README_files/hist.png
doc/_static/README_files/hist_step_fill.png
doc/_static/README_files/jitter_summary.png
doc/_static/README_files/jitter_violin.png
doc/_static/README_files/kde.png
doc/_static/README_files/line.png
doc/_static/README_files/loading_plot_metadata.png
doc/_static/README_files/paired.png
doc/_static/README_files/percent.png
doc/_static/README_files/scatter.png
doc/_static/README_files/violin.png
lithos/__init__.py
lithos/plotting/__init__.py
lithos/plotting/matplotlib_plotter.py
lithos/plotting/plot_utils.py
lithos/plotting/plot_class/__init__.py
lithos/plotting/plot_class/base_class.py
lithos/plotting/plot_class/categorical_class.py
lithos/plotting/plot_class/line_class.py
lithos/plotting/processing/__init__.py
lithos/plotting/processing/base_processor.py
lithos/plotting/processing/categorical_processor.py
lithos/plotting/processing/line_processor.py
lithos/stats/__init__.py
lithos/stats/circular_stats.py
lithos/stats/curve_fit.py
lithos/stats/ecdf.py
lithos/stats/histogram_funcs.py
lithos/stats/kde_func.py
lithos/types/__init__.py
lithos/types/basic_types.py
lithos/types/plot_input.py
lithos/types/plot_types.py
lithos/utils/__init__.py
lithos/utils/data_generation.py
lithos/utils/dataholder.py
lithos/utils/metadata_utils.py
lithos/utils/transforms.py
lithos-0.1.10.dist-info/licenses/LICENSE.md
tests/__init__.py
tests/colors_test.py
tests/conftest.py
tests/datagenerator_test.py
tests/metadata_test.py
tests/plot_utils_test.py
tests/dataholder/__init__.py
tests/dataholder/dataholder_dict_test.py
tests/dataholder/dataholder_numpy_test.py
tests/dataholder/dataholder_pd_test.py
tests/dataholder/dataholder_test_class.py
lithos-0.1.10.dist-info/METADATA
lithos-0.1.10.dist-info/WHEEL
lithos-0.1.10.dist-info/top_level.txt
lithos-0.1.10.dist-info/RECORD
