Metadata-Version: 2.4
Name: lithos
Version: 0.1.10
Summary: Lithos: plotting package for categorical and nested data.
Author-email: Lars Henrik Nelson <larshnelson@protonmail.com>
Maintainer-email: Lars Henrik Nelson <larshnelson@protonmail.com>
License-Expression: BSD-3-Clause
Project-URL: Downloads, https://github.com/LarsHenrikNelson/lithos
Classifier: Intended Audience :: Science/Research
Classifier: Programming Language :: Python :: 3.10
Classifier: Programming Language :: Python :: 3.11
Classifier: Programming Language :: Python :: 3.12
Classifier: Topic :: Scientific/Engineering :: Visualization
Classifier: Topic :: Multimedia :: Graphics
Classifier: Operating System :: OS Independent
Classifier: Framework :: Matplotlib
Requires-Python: >=3.10
License-File: LICENSE.md
Requires-Dist: colorcet
Requires-Dist: KDEpy
Requires-Dist: matplotlib
Requires-Dist: numba
Requires-Dist: numpy>1.24.0
Requires-Dist: pandas
Requires-Dist: scipy
Requires-Dist: typing-extensions
Provides-Extra: testing
Requires-Dist: pytest; extra == "testing"
Requires-Dist: pytest-cov; extra == "testing"
Provides-Extra: docs
Requires-Dist: nbconvert; extra == "docs"
Dynamic: license-file
